{
    "key": "group_6970ca10912f2",
    "title": "Block: Pros Cons",
    "fields": [
        {
            "key": "field_6970ca119a4a2",
            "label": "Block Pros Cons",
            "name": "block_pros_cons",
            "aria-label": "",
            "type": "group",
            "instructions": "",
            "required": 0,
            "conditional_logic": 0,
            "wrapper": {
                "width": "",
                "class": "",
                "id": ""
            },
            "layout": "block",
            "sub_fields": [
                {
                    "key": "field_6970ca309a4a3",
                    "label": "Title",
                    "name": "title",
                    "aria-label": "",
                    "type": "text",
                    "instructions": "",
                    "required": 0,
                    "conditional_logic": 0,
                    "wrapper": {
                        "width": "",
                        "class": "",
                        "id": ""
                    },
                    "default_value": "",
                    "maxlength": "",
                    "placeholder": "",
                    "prepend": "",
                    "append": ""
                },
                {
                    "key": "field_6970ca349a4a4",
                    "label": "Text",
                    "name": "text",
                    "aria-label": "",
                    "type": "textarea",
                    "instructions": "",
                    "required": 0,
                    "conditional_logic": 0,
                    "wrapper": {
                        "width": "",
                        "class": "",
                        "id": ""
                    },
                    "default_value": "",
                    "maxlength": "",
                    "rows": "",
                    "placeholder": "",
                    "new_lines": ""
                },
                {
                    "key": "field_6970ca409a4a5",
                    "label": "Pros Title",
                    "name": "pros_title",
                    "aria-label": "",
                    "type": "text",
                    "instructions": "",
                    "required": 0,
                    "conditional_logic": 0,
                    "wrapper": {
                        "width": "",
                        "class": "",
                        "id": ""
                    },
                    "default_value": "",
                    "maxlength": "",
                    "placeholder": "",
                    "prepend": "",
                    "append": ""
                },
                {
                    "key": "field_6970ca479a4a6",
                    "label": "Pros List",
                    "name": "pros_list",
                    "aria-label": "",
                    "type": "repeater",
                    "instructions": "",
                    "required": 0,
                    "conditional_logic": 0,
                    "wrapper": {
                        "width": "",
                        "class": "",
                        "id": ""
                    },
                    "layout": "table",
                    "pagination": 0,
                    "min": 0,
                    "max": 0,
                    "collapsed": "",
                    "button_label": "Add Row",
                    "rows_per_page": 20,
                    "sub_fields": [
                        {
                            "key": "field_6970ca509a4a7",
                            "label": "Item",
                            "name": "item",
                            "aria-label": "",
                            "type": "text",
                            "instructions": "",
                            "required": 0,
                            "conditional_logic": 0,
                            "wrapper": {
                                "width": "",
                                "class": "",
                                "id": ""
                            },
                            "default_value": "",
                            "maxlength": "",
                            "placeholder": "",
                            "prepend": "",
                            "append": "",
                            "parent_repeater": "field_6970ca479a4a6"
                        }
                    ]
                },
                {
                    "key": "field_6970ca569a4a8",
                    "label": "Cons Title",
                    "name": "cons_title",
                    "aria-label": "",
                    "type": "text",
                    "instructions": "",
                    "required": 0,
                    "conditional_logic": 0,
                    "wrapper": {
                        "width": "",
                        "class": "",
                        "id": ""
                    },
                    "default_value": "",
                    "maxlength": "",
                    "placeholder": "",
                    "prepend": "",
                    "append": ""
                },
                {
                    "key": "field_6970ca5c9a4a9",
                    "label": "Cons List",
                    "name": "cons_list",
                    "aria-label": "",
                    "type": "repeater",
                    "instructions": "",
                    "required": 0,
                    "conditional_logic": 0,
                    "wrapper": {
                        "width": "",
                        "class": "",
                        "id": ""
                    },
                    "layout": "table",
                    "pagination": 0,
                    "min": 0,
                    "max": 0,
                    "collapsed": "",
                    "button_label": "Add Row",
                    "rows_per_page": 20,
                    "sub_fields": [
                        {
                            "key": "field_6970ca649a4aa",
                            "label": "Item",
                            "name": "item",
                            "aria-label": "",
                            "type": "text",
                            "instructions": "",
                            "required": 0,
                            "conditional_logic": 0,
                            "wrapper": {
                                "width": "",
                                "class": "",
                                "id": ""
                            },
                            "default_value": "",
                            "maxlength": "",
                            "placeholder": "",
                            "prepend": "",
                            "append": "",
                            "parent_repeater": "field_6970ca5c9a4a9"
                        }
                    ]
                }
            ]
        }
    ],
    "location": [
        [
            {
                "param": "block",
                "operator": "==",
                "value": "acf\/pros-cons"
            }
        ]
    ],
    "menu_order": 0,
    "position": "normal",
    "style": "default",
    "label_placement": "top",
    "instruction_placement": "label",
    "hide_on_screen": "",
    "active": true,
    "description": "",
    "show_in_rest": 0,
    "modified": 1779881188
}
